mailz/__init__.py
mailz/builder.py
mailz/cli/__init__.py
mailz/cli/new.py
mailz/cli/run.py
mailz/config.py
mailz/exceptions.py
mailz/mail.py
mailz/paths.py
mailz/runner.py
mailz/sender.py
mailz/target.py
mailz-1.0.0.dist-info/entry_points.txt
mailz-1.0.0.dist-info/LICENSE
mailz-1.0.0.dist-info/WHEEL
mailz-1.0.0.dist-info/METADATA
mailz-1.0.0.dist-info/RECORD
