Metadata-Version: 2.1
Name: mailz
Version: 1.0.0
Summary: Basic mailing tool.
Home-page: https://github.com/m09/mailz
License: Apache-2.0
Author: m09
Author-email: 142691+m09@users.noreply.github.com
Requires-Python: >=3.7,<4.0
Classifier: License :: OSI Approved :: Apache Software License
Classifier: Programming Language :: Python :: 3
Classifier: Programming Language :: Python :: 3.7
Classifier: Programming Language :: Python :: 3.8
Classifier: Programming Language :: Python :: 3.9
Requires-Dist: GitPython (>=3.1.11,<4.0.0)
Requires-Dist: Jinja2 (>=2.11.1,<3.0.0)
Requires-Dist: PyYAML (>=5.3.1,<6.0.0)
Requires-Dist: appdirs (>=1.4.4,<2.0.0)
Requires-Dist: click (>=7.1.1,<8.0.0)
Requires-Dist: coloredlogs (>=14.0,<15.0)
Requires-Dist: pytest (>=6.1.2,<7.0.0)
Requires-Dist: pytest-cov (>=2.10.1,<3.0.0)
Requires-Dist: sendgrid (>=6.4.7,<7.0.0)
Requires-Dist: tqdm (>=4.50.2,<5.0.0)
